[
  {
    "date": "2026-05-03",
    "slug": "2026-05-03",
    "title": "Tokenized Real Estate Market Update — May 3, 2026",
    "summary": "The tokenized real estate market continues to offer accessible entry points for retail investors seeking passive income. Across 459 active listings on Lofty and RealT, the average net yield currently sits at 10.1%, reflecting a diverse range of residential properties primarily concentrated in US markets.\n\nTop performers this period include 15 Wilshire Blvd in Lubbock, delivering 29.67% net yield. Detroit leads in listing volume with 169 available properties, offering investors meaningful diversification within a single metro area.\n\nInvestors should review occupancy rates, fee structures, and platform-specific terms before committing capital. Brickwise scores each property on yield, risk, neighborhood quality, and token fair value to help surface the most compelling opportunities at any given time.",
    "highlights": [
      "459 tokenized properties tracked across Lofty and RealT",
      "Average net yield: 10.1% across all active listings",
      "Top yield: 29.67% — 15 Wilshire Blvd, Lubbock",
      "Detroit leads with 169 available listings",
      "Average Brickwise score: 72/100"
    ],
    "stats": {
      "totalListings": 459,
      "avgYield": 10.1,
      "avgScore": 72,
      "topYield": 29.67,
      "topYieldCity": "Lubbock"
    },
    "topProperties": [
      {
        "id": 101,
        "name": "11125 Lawnhaven Rd",
        "yield": 13.03,
        "score": 82,
        "city": "Dallas"
      },
      {
        "id": 110,
        "name": "6601 E Hearn Rd",
        "yield": 28.09,
        "score": 82,
        "city": "Scottsdale"
      },
      {
        "id": 114,
        "name": "4506 S Fallwood Ct",
        "yield": 15.1,
        "score": 82,
        "city": "Columbia"
      },
      {
        "id": 118,
        "name": "581 San Francisco St",
        "yield": 20.34,
        "score": 82,
        "city": "Las Cruces"
      },
      {
        "id": 131,
        "name": "1190 Ridgetop Ave",
        "yield": 14.29,
        "score": 82,
        "city": "Las Cruces"
      }
    ]
  },
  {
    "date": "2026-05-02",
    "slug": "2026-05-02",
    "title": "Tokenized Real Estate Market Update — May 2, 2026",
    "summary": "The tokenized real estate market continues to offer accessible entry points for retail investors seeking passive income. Across 286 active listings on Lofty and RealT, the average net yield currently sits at 10.7%, reflecting a diverse range of residential properties primarily concentrated in US markets.\n\nTop performers this period include 15 Wilshire Blvd in Lubbock, delivering 29.67% net yield. Detroit leads in listing volume with 41 available properties, offering investors meaningful diversification within a single metro area.\n\nInvestors should review occupancy rates, fee structures, and platform-specific terms before committing capital. Brickwise scores each property on yield, risk, neighborhood quality, and token fair value to help surface the most compelling opportunities at any given time.",
    "highlights": [
      "286 tokenized properties tracked across Lofty and RealT",
      "Average net yield: 10.7% across all active listings",
      "Top yield: 29.67% — 15 Wilshire Blvd, Lubbock",
      "Detroit leads with 41 available listings",
      "Average Brickwise score: 72/100"
    ],
    "stats": {
      "totalListings": 286,
      "avgYield": 10.7,
      "avgScore": 72,
      "topYield": 29.67,
      "topYieldCity": "Lubbock"
    },
    "topProperties": [
      {
        "id": 101,
        "name": "11125 Lawnhaven Rd",
        "yield": 13.03,
        "score": 82,
        "city": "Dallas"
      },
      {
        "id": 110,
        "name": "6601 E Hearn Rd",
        "yield": 27.94,
        "score": 82,
        "city": "Scottsdale"
      },
      {
        "id": 114,
        "name": "4506 S Fallwood Ct",
        "yield": 15.1,
        "score": 82,
        "city": "Columbia"
      },
      {
        "id": 118,
        "name": "581 San Francisco St",
        "yield": 20.44,
        "score": 82,
        "city": "Las Cruces"
      },
      {
        "id": 131,
        "name": "1190 Ridgetop Ave",
        "yield": 14.29,
        "score": 82,
        "city": "Las Cruces"
      }
    ]
  },
  {
    "date": "2026-05-01",
    "slug": "2026-05-01",
    "title": "Tokenized Real Estate Market Update — May 1, 2026",
    "summary": "The tokenized real estate market continues to offer accessible entry points for retail investors seeking passive income. Across 248 active listings on Lofty and RealT, the average net yield currently sits at 10.8%, reflecting a diverse range of residential properties primarily concentrated in US markets.\n\nTop performers this period include 15 Wilshire Blvd in Lubbock, delivering 29.65% net yield. Cleveland leads in listing volume with 17 available properties, offering investors meaningful diversification within a single metro area.\n\nInvestors should review occupancy rates, fee structures, and platform-specific terms before committing capital. Brickwise scores each property on yield, risk, neighborhood quality, and token fair value to help surface the most compelling opportunities at any given time.",
    "highlights": [
      "248 tokenized properties tracked across Lofty and RealT",
      "Average net yield: 10.8% across all active listings",
      "Top yield: 29.65% — 15 Wilshire Blvd, Lubbock",
      "Cleveland leads with 17 available listings",
      "Average Brickwise score: 73/100"
    ],
    "stats": {
      "totalListings": 248,
      "avgYield": 10.8,
      "avgScore": 73,
      "topYield": 29.65,
      "topYieldCity": "Lubbock"
    },
    "topProperties": [
      {
        "id": 101,
        "name": "11125 Lawnhaven Rd",
        "yield": 15.15,
        "score": 82,
        "city": "Dallas"
      },
      {
        "id": 110,
        "name": "6601 E Hearn Rd",
        "yield": 27.88,
        "score": 82,
        "city": "Scottsdale"
      },
      {
        "id": 114,
        "name": "4506 S Fallwood Ct",
        "yield": 15.1,
        "score": 82,
        "city": "Columbia"
      },
      {
        "id": 118,
        "name": "581 San Francisco St",
        "yield": 20.44,
        "score": 82,
        "city": "Las Cruces"
      },
      {
        "id": 131,
        "name": "1190 Ridgetop Ave",
        "yield": 14.29,
        "score": 82,
        "city": "Las Cruces"
      }
    ]
  },
  {
    "date": "2026-04-30",
    "slug": "2026-04-30",
    "title": "Tokenized Real Estate Market Update — April 30, 2026",
    "summary": "The tokenized real estate market continues to offer accessible entry points for retail investors seeking passive income. Across 96 active listings on Lofty and RealT, the average net yield currently sits at 12%, reflecting a diverse range of residential properties primarily concentrated in US markets.\n\nTop performers this period include 15 Wilshire Blvd in Lubbock, delivering 29.65% net yield. Cleveland leads in listing volume with 15 available properties, offering investors meaningful diversification within a single metro area.\n\nInvestors should review occupancy rates, fee structures, and platform-specific terms before committing capital. Brickwise scores each property on yield, risk, neighborhood quality, and token fair value to help surface the most compelling opportunities at any given time.",
    "highlights": [
      "96 tokenized properties tracked across Lofty and RealT",
      "Average net yield: 12% across all active listings",
      "Top yield: 29.65% — 15 Wilshire Blvd, Lubbock",
      "Cleveland leads with 15 available listings",
      "Average Brickwise score: 73/100"
    ],
    "stats": {
      "totalListings": 96,
      "avgYield": 12,
      "avgScore": 73,
      "topYield": 29.65,
      "topYieldCity": "Lubbock"
    },
    "topProperties": [
      {
        "id": 101,
        "name": "11125 Lawnhaven Rd",
        "yield": 14.48,
        "score": 82,
        "city": "Dallas"
      },
      {
        "id": 110,
        "name": "6601 E Hearn Rd",
        "yield": 29.25,
        "score": 82,
        "city": "Scottsdale"
      },
      {
        "id": 114,
        "name": "4506 S Fallwood Ct",
        "yield": 15.14,
        "score": 82,
        "city": "Columbia"
      },
      {
        "id": 118,
        "name": "581 San Francisco St",
        "yield": 19.35,
        "score": 82,
        "city": "Las Cruces"
      },
      {
        "id": 131,
        "name": "1190 Ridgetop Ave",
        "yield": 14.29,
        "score": 82,
        "city": "Las Cruces"
      }
    ]
  }
]
